steamwine/__init__.py
steamwine/steamwine.py
steamwine/utils.py
steamwine-0.0.1.dist-info/WHEEL
steamwine-0.0.1.dist-info/METADATA
steamwine-0.0.1.dist-info/RECORD
