Metadata-Version: 2.1
Name: steamwine
Version: 0.0.1
Summary: Simple work with API Steam
Home-page: https://github.com/Fsoky/steamwine
Author: Fsoky
Author-email: cyberuest0x12@gmail.com
Requires-Python: >=3.8,<4.0
Classifier: Programming Language :: Python :: 3
Classifier: Programming Language :: Python :: 3.8
Requires-Dist: aiohttp (>=3.8.1,<4.0.0)
